<?xml version="1.0" encoding="UTF-8"?>
<kcfg xmlns="http://www.kde.org/standards/kcfg/1.0">
    <kcfgfile name=""/>
    <group name="General">
        <entry name="accessToken" type="String">
            <default></default>
        </entry>
        <entry name="calendarId" type="String">
            <default></default>
        </entry>
        <entry name="provider" type="String">
            <default></default>
        </entry>
        <entry name="nextcloudServer" type="String">
            <default></default>
        </entry>
        <entry name="daysToShow" type="Int">
            <default></default>
        </entry>
        <entry name="googleClientId" type="String">
            <default></default>
        </entry>
        <entry name="googleClientSecret" type="String">
            <default></default>
        </entry>
        <entry name="nextcloudClientId" type="String">
            <default></default>
        </entry>
        <entry name="nextcloudClientSecret" type="String">
            <default></default>
        </entry>
        <entry name="nextcloudAuthEndpoint" type="String">
            <default></default>
        </entry>
        <entry name="nextcloudTokenEndpoint" type="String">
            <default></default>
        </entry>
    </group>
</kcfg>

